<odoo>
  <data>
    <record id='assistantndniletra' model='party.assistant'>
      <field name='dni'>ndniletra</field>
      <field name='Birthday'>Birthday</field>
      <field name='email'>email</field>
    </record>
    <record id='assistant12346935F' model='party.assistant'>
      <field name='dni'>12346935F</field>
      <field name='Birthday'>2/14/1996</field>
      <field name='email'>ddurrell0@pinterest.com</field>
    </record>
    <record id='assistant79436973F' model='party.assistant'>
      <field name='dni'>79436973F</field>
      <field name='Birthday'>3/13/1992</field>
      <field name='email'>cmewett1@wikispaces.com</field>
    </record>
    <record id='assistant64522878M' model='party.assistant'>
      <field name='dni'>64522878M</field>
      <field name='Birthday'>6/9/2018</field>
      <field name='email'>fmckinnon2@google.es</field>
    </record>
    <record id='assistant29371073F' model='party.assistant'>
      <field name='dni'>29371073F</field>
      <field name='Birthday'>9/17/2020</field>
      <field name='email'>ipiddletown3@shareasale.com</field>
    </record>
    <record id='assistant89964754M' model='party.assistant'>
      <field name='dni'>89964754M</field>
      <field name='Birthday'>9/16/1995</field>
      <field name='email'>lgarvagh4@amazon.co.jp</field>
    </record>
    <record id='assistant42273788M' model='party.assistant'>
      <field name='dni'>42273788M</field>
      <field name='Birthday'>11/29/2005</field>
      <field name='email'>amarr5@photobucket.com</field>
    </record>
    <record id='assistant34293483F' model='party.assistant'>
      <field name='dni'>34293483F</field>
      <field name='Birthday'>12/2/1996</field>
      <field name='email'>nbrands6@biblegateway.com</field>
    </record>
    <record id='assistant87119844F' model='party.assistant'>
      <field name='dni'>87119844F</field>
      <field name='Birthday'>9/22/1994</field>
      <field name='email'>ccandwell7@simplemachines.org</field>
    </record>
    <record id='assistant20125000F' model='party.assistant'>
      <field name='dni'>20125000F</field>
      <field name='Birthday'>8/28/2001</field>
      <field name='email'>ghapps8@tamu.edu</field>
    </record>
    <record id='assistant76281161M' model='party.assistant'>
      <field name='dni'>76281161M</field>
      <field name='Birthday'>12/23/2010</field>
      <field name='email'>hegerton9@google.fr</field>
    </record>
  </data>
</odoo>
